{"cameraMode":{"drawMode":0,"name":"Shaded","section":"Shading Mode"},"sceneLighting":true,"audioPlay":false,"sceneViewState":{"m_AlwaysRefresh":false,"showFog":true,"showSkybox":true,"showFlares":true,"showImageEffects":true,"showParticleSystems":true,"showVisualEffectGraphs":true,"m_FxEnabled":true},"in2DMode":false,"pivot":{"x":-9.569799423217774,"y":-16.67279624938965,"z":18.564231872558595},"rotation":{"x":-0.3242449164390564,"y":0.24361667037010194,"z":-0.08682461827993393,"w":-0.9099467992782593},"size":23.510160446166993,"orthographic":false}